asana_cli/__init__.py
asana_cli/cli.py
asana_cli/version.py
asana_cli-0.0.3.dist-info/DESCRIPTION.rst
asana_cli-0.0.3.dist-info/METADATA
asana_cli-0.0.3.dist-info/RECORD
asana_cli-0.0.3.dist-info/WHEEL
asana_cli-0.0.3.dist-info/entry_points.txt
asana_cli-0.0.3.dist-info/metadata.json
asana_cli-0.0.3.dist-info/top_level.txt
